Login_Appl/Login.py
Login_Appl/__init__.py
Login_Appl/login_holder.py
kmmod-0.1.dist-info/LICENSE.txt
kmmod-0.1.dist-info/METADATA
kmmod-0.1.dist-info/WHEEL
kmmod-0.1.dist-info/top_level.txt
kmmod-0.1.dist-info/RECORD
