Metadata-Version: 2.1
Name: kmmod
Version: 0.1
Summary: Python creations
Author: Kodjo Messie
Author-email: kodjomessie@gmail.com
Classifier: Programming Language :: Python :: 3
Classifier: License :: OSI Approved :: MIT License
License-File: LICENSE.txt
